iris_emotion/SA_API.py
iris_emotion/__init__.py
iris_emotion/tokenizer.pickle
iris_emotion/SA_Model_Final_v8/__init__.py
iris_emotion/SA_Model_Final_v8/keras_metadata.pb
iris_emotion/SA_Model_Final_v8/saved_model.pb
iris_emotion/SA_Model_Final_v8/assets/__init__.py
iris_emotion/SA_Model_Final_v8/variables/__init__.py
iris_emotion/SA_Model_Final_v8/variables/variables.data-00000-of-00001
iris_emotion/SA_Model_Final_v8/variables/variables.index
iris_emotion-0.2.0.dist-info/LICENSE
iris_emotion-0.2.0.dist-info/METADATA
iris_emotion-0.2.0.dist-info/WHEEL
iris_emotion-0.2.0.dist-info/top_level.txt
iris_emotion-0.2.0.dist-info/RECORD
