Metadata-Version: 2.1
Name: iris-emotion
Version: 0.2.0
Summary: Detect emotions in text.
Home-page: https://github.com/Anjanaval/IRIS-Emotion.git
Author: Anjana Valsalan
Author-email: anjana.valsalan@my.uwi.edu
License: MIT
Keywords: Emotion Detection,Sentiment Analysis,Natural Language Processing
Platform: UNKNOWN
Classifier: Development Status :: 5 - Production/Stable
Classifier: Intended Audience :: Developers
Classifier: Topic :: Software Development :: Build Tools
Classifier: License :: OSI Approved :: MIT License
Classifier: Programming Language :: Python :: 3.8
License-File: LICENSE
Requires-Dist: tensorflow
Requires-Dist: numpy
